[
  {
    "name": "Anthony",
    "PID": 0,
    "pastseasons": [
      true,
      true,
      true
    ],
    "active": true,
    "playing": true,
    "jointimestamp": 1672531200,
    "quittimestamp": 0,
    "iconcolor": "#41a308",
    "inventory": []
  },
  {
    "name": "Xeya",
    "PID": 1,
    "pastseasons": [
      true,
      true,
      true
    ],
    "active": false,
    "playing": true,
    "jointimestamp": 1672531200,
    "quittimestamp": 0,
    "iconcolor": "#ee9bad",
    "inventory": []
  },
  {
    "name": "lime",
    "PID": 2,
    "pastseasons": [
      true,
      true,
      true
    ],
    "active": false,
    "playing": true,
    "jointimestamp": 1672531200,
    "quittimestamp": 0,
    "iconcolor": "#c4faf8",
    "inventory": []
  },
  {
    "name": "Fathom",
    "PID": 3,
    "pastseasons": [
      true,
      true,
      true
    ],
    "active": false,
    "playing": true,
    "jointimestamp": 1672531200,
    "quittimestamp": 0,
    "iconcolor": "#bf8dd0",
    "inventory": []
  },
  {
    "name": "Ryan",
    "PID": 4,
    "pastseasons": [
      true,
      true,
      true
    ],
    "active": true,
    "playing": true,
    "jointimestamp": 1672531200,
    "quittimestamp": 0,
    "iconcolor": "#5d3fd3",
    "inventory": []
  },
  {
    "name": "flora246",
    "PID": 5,
    "pastseasons": [
      false,
      false,
      true
    ],
    "active": false,
    "playing": true,
    "jointimestamp": 1672531200,
    "quittimestamp": 0,
    "iconcolor": "#d2d2d2",
    "inventory": []
  },
  {
    "name": "will.b393",
    "PID": 6,
    "pastseasons": [
      false,
      false,
      false
    ],
    "active": true,
    "playing": true,
    "jointimestamp": 1672531200,
    "quittimestamp": 0,
    "iconcolor": "#000000",
    "inventory": []
  }
]